be/rendering_templates.py
be/api/authenticate.py
be/api/centralized_auth.py
be/api/debug.py
be/api/jwt_utils.py
be/api/passkey_store.py
be/api/profile.py
be/api/register.py
be/api/render.py
be/api/s3_storage.py
be/api/test_creds.py
be/api/admin/users.py
fe/static/activity.html
fe/static/admin.html
fe/static/auth-helper.js
fe/static/auth-renderer.css
fe/static/auth-renderer.js
fe/static/help.html
fe/static/index.html
fe/static/profile.html
fe/static/welcome.html
app.json
avyas_aurica_base_apps_auth_app-2.5.3.dist-info/METADATA
avyas_aurica_base_apps_auth_app-2.5.3.dist-info/WHEEL
avyas_aurica_base_apps_auth_app-2.5.3.dist-info/RECORD
