Metadata-Version: 2.4
Name: avyas-aurica-base-apps-auth-app
Version: 2.5.3
Summary: Aurica app: auth-app
Requires-Python: >=3.11
Requires-Dist: fastapi>=0.104.0
Requires-Dist: uvicorn>=0.24.0
